bceauth/__init__.py
bceauth/bce_base_client.py
bceauth/bce_client_configuration.py
bceauth/bce_response.py
bceauth/compat.py
bceauth/exception.py
bceauth/handler.py
bceauth/protocol.py
bceauth/region.py
bceauth/utils.py
bceauth/auth/__init__.py
bceauth/auth/bce_credentials.py
bceauth/auth/bce_v1_signer.py
bceauth/auth/iam_credentials.py
bceauth/auth/idaas_credentials.py
bceauth/cache/__init__.py
bceauth/cache/token_cache.py
bceauth/http/__init__.py
bceauth/http/bce_http_client.py
bceauth/http/handler.py
bceauth/http/http_content_types.py
bceauth/http/http_headers.py
bceauth/http/http_methods.py
bceauth/middleware/__init__.py
bceauth/middleware/auth/__init__.py
bceauth/middleware/auth/const.py
bceauth/middleware/auth/iam_session.py
bceauth/middleware/auth/idaas_session.py
bceauth/middleware/auth/utils.py
bceauth/retry/__init__.py
bceauth/retry/retry_policy.py
bceauth/services/__init__.py
bceauth/services/iam/__init__.py
bceauth/services/iam/iam_client.py
bceauth/services/idaas/__init__.py
bceauth/services/idaas/idaas_client.py
bceauth/services/sts/__init__.py
bceauth/services/sts/sts_client.py
bceauth-0.0.1.dist-info/METADATA
bceauth-0.0.1.dist-info/WHEEL
bceauth-0.0.1.dist-info/top_level.txt
bceauth-0.0.1.dist-info/RECORD
